anshukak/__init__.py
anshukak/main.py
anshukak-1.0.dist-info/METADATA
anshukak-1.0.dist-info/WHEEL
anshukak-1.0.dist-info/entry_points.txt
anshukak-1.0.dist-info/top_level.txt
anshukak-1.0.dist-info/RECORD
