Metadata-Version: 2.1
Name: anshukak
Version: 1.0
Requires-Dist: requests
Requires-Dist: pyperclip
